screenshot_guard/__init__.py
screenshot_guard/cli.py
screenshot_guard/detector.py
screenshot_guard/ocr.py
screenshot_guard/scanner.py
screenshot_guard/patterns/__init__.py
screenshot_guard/patterns/aws.py
screenshot_guard/patterns/azure.py
screenshot_guard/patterns/base.py
screenshot_guard/patterns/gcp.py
screenshot_guard/patterns/generic.py
screenshot_guard/patterns/github.py
screenshot_guard/patterns/registry.py
screenshot_guard/reporters/__init__.py
screenshot_guard/reporters/json_reporter.py
screenshot_guard/reporters/markdown_reporter.py
screenshot_guard/reporters/sarif_reporter.py
screenshot_guard-0.1.0.dist-info/METADATA
screenshot_guard-0.1.0.dist-info/WHEEL
screenshot_guard-0.1.0.dist-info/entry_points.txt
screenshot_guard-0.1.0.dist-info/licenses/LICENSE
screenshot_guard-0.1.0.dist-info/RECORD
