Metadata-Version: 2.4
Name: screenshot-guard
Version: 0.1.0
Summary: Secret Scanner with OCR Superpowers - Finds secrets in code AND screenshots
Project-URL: Homepage, https://github.com/Keyvanhardani/screenshot-guard
Project-URL: Documentation, https://github.com/Keyvanhardani/screenshot-guard#readme
Project-URL: Repository, https://github.com/Keyvanhardani/screenshot-guard
Project-URL: Issues, https://github.com/Keyvanhardani/screenshot-guard/issues
Author-email: Keyvan Hardani <keyvan@keyvan.ai>
License-Expression: Apache-2.0
License-File: LICENSE
Keywords: ci-cd,devsecops,github-action,ocr,scanner,screenshot,secrets,security
Classifier: Development Status :: 4 - Beta
Classifier: Intended Audience :: Developers
Classifier: License :: OSI Approved :: Apache Software License
Classifier: Programming Language :: Python :: 3
Classifier: Programming Language :: Python :: 3.10
Classifier: Programming Language :: Python :: 3.11
Classifier: Programming Language :: Python :: 3.12
Classifier: Topic :: Security
Classifier: Topic :: Software Development :: Quality Assurance
Requires-Python: >=3.10
Requires-Dist: click>=8.0
Requires-Dist: pathspec>=0.11
Requires-Dist: pydantic>=2.0
Requires-Dist: rich>=13.0
Provides-Extra: all
Requires-Dist: german-ocr[llamacpp]>=0.1.0; extra == 'all'
Requires-Dist: mypy>=1.0; extra == 'all'
Requires-Dist: pre-commit>=3.0; extra == 'all'
Requires-Dist: pytest-cov>=4.0; extra == 'all'
Requires-Dist: pytest>=7.0; extra == 'all'
Requires-Dist: ruff>=0.1; extra == 'all'
Provides-Extra: dev
Requires-Dist: mypy>=1.0; extra == 'dev'
Requires-Dist: pre-commit>=3.0; extra == 'dev'
Requires-Dist: pytest-cov>=4.0; extra == 'dev'
Requires-Dist: pytest>=7.0; extra == 'dev'
Requires-Dist: ruff>=0.1; extra == 'dev'
Provides-Extra: ocr
Requires-Dist: german-ocr[llamacpp]>=0.1.0; extra == 'ocr'
Provides-Extra: ollama
Requires-Dist: german-ocr[ollama]>=0.1.0; extra == 'ollama'
